PrSpider/PrSpiders.py
PrSpider/Request.py
PrSpider/__init__.py
PrSpider/cssApi.py
PrSpider/dateParse.py
PrSpider/log.py
PrSpider/pipelines.py
PrSpider/pyconn.py
PrSpider/settion.py
PrSpider/useragent.py
PrSpider/utils.py
PrSpider/xpathApi.py
pkg/__init__.py
pkg/prspider/PrSpider_CMD.py
pkg/prspider/PrSpider_run.py
pkg/prspider/__init__.py
pkg/prspider/start.py
requestXpath/__init__.py
requestXpath/pxpath.py
requestXpath/requestXpath.py
requestXpath/useragent.py
PrSpiders-2.1.6.dist-info/LICENSE.txt
PrSpiders-2.1.6.dist-info/METADATA
PrSpiders-2.1.6.dist-info/WHEEL
PrSpiders-2.1.6.dist-info/entry_points.txt
PrSpiders-2.1.6.dist-info/top_level.txt
PrSpiders-2.1.6.dist-info/RECORD
