Metadata-Version: 2.1
Name: PrSpiders
Version: 2.1.6
Summary: Inherit the requests module, add xpath functionality to expand the API, and handle request failures and retries
Home-page: https://github.com/peng0928/prequests
Author: penr
Author-email: 1944542244@qq.com
License: MIT
License-File: LICENSE.txt
Requires-Dist: requests
Requires-Dist: urllib3
Requires-Dist: redis
Requires-Dist: PrSpiders
Requires-Dist: loguru
Requires-Dist: pymysql
Requires-Dist: parsel
